CONTRIBUTING.md
tp53/__init__.py
tp53/py.typed
tp53/seshat/__init__.py
tp53/seshat/_exceptions.py
tp53/seshat/find_in_gmail/__init__.py
tp53/seshat/find_in_gmail/__main__.py
tp53/seshat/find_in_gmail/_find_in_gmail.py
tp53/seshat/upload_vcf/__init__.py
tp53/seshat/upload_vcf/__main__.py
tp53/seshat/upload_vcf/_upload_vcf.py
tp53-0.13.0.dist-info/METADATA
tp53-0.13.0.dist-info/WHEEL
tp53-0.13.0.dist-info/RECORD
